datasette/__init__.py
datasette/__main__.py
datasette/actor_auth_cookie.py
datasette/app.py
datasette/blob_renderer.py
datasette/cli.py
datasette/database.py
datasette/default_magic_parameters.py
datasette/default_menu_links.py
datasette/default_permissions.py
datasette/facets.py
datasette/filters.py
datasette/forbidden.py
datasette/handle_exception.py
datasette/hookspecs.py
datasette/inspect.py
datasette/plugins.py
datasette/renderer.py
datasette/sql_functions.py
datasette/tracer.py
datasette/url_builder.py
datasette/version.py
datasette/publish/__init__.py
datasette/publish/cloudrun.py
datasette/publish/common.py
datasette/publish/heroku.py
datasette/static/app.css
datasette/static/cm-resize-1.0.1.min.js
datasette/static/codemirror-5.57.0-sql.min.js
datasette/static/codemirror-5.57.0.min.css
datasette/static/codemirror-5.57.0.min.js
datasette/static/favicon.png
datasette/static/sql-formatter-2.3.3.min.js
datasette/static/table.js
datasette/templates/_close_open_menus.html
datasette/templates/_codemirror.html
datasette/templates/_codemirror_foot.html
datasette/templates/_crumbs.html
datasette/templates/_description_source_license.html
datasette/templates/_facet_results.html
datasette/templates/_footer.html
datasette/templates/_suggested_facets.html
datasette/templates/_table.html
datasette/templates/allow_debug.html
datasette/templates/base.html
datasette/templates/database.html
datasette/templates/error.html
datasette/templates/index.html
datasette/templates/logout.html
datasette/templates/messages_debug.html
datasette/templates/patterns.html
datasette/templates/permissions_debug.html
datasette/templates/query.html
datasette/templates/row.html
datasette/templates/show_json.html
datasette/templates/table.html
datasette/utils/__init__.py
datasette/utils/asgi.py
datasette/utils/baseconv.py
datasette/utils/internal_db.py
datasette/utils/shutil_backport.py
datasette/utils/sqlite.py
datasette/utils/testing.py
datasette/vendored/__init__.py
datasette-0.65.dist-info/LICENSE
datasette-0.65.dist-info/METADATA
datasette-0.65.dist-info/WHEEL
datasette-0.65.dist-info/entry_points.txt
datasette-0.65.dist-info/top_level.txt
datasette-0.65.dist-info/RECORD
