Metadata-Version: 2.1
Name: datasette
Version: 0.65
Summary: An open source multi-tool for exploring and publishing data
Home-page: https://datasette.io/
Author: Simon Willison
License: Apache License, Version 2.0
Project-URL: Documentation, https://docs.datasette.io/en/stable/
Project-URL: Changelog, https://docs.datasette.io/en/stable/changelog.html
Project-URL: Live demo, https://latest.datasette.io/
Project-URL: Source code, https://github.com/simonw/datasette
Project-URL: Issues, https://github.com/simonw/datasette/issues
Project-URL: CI, https://github.com/simonw/datasette/actions?query=workflow%3ATest
Classifier: Development Status :: 4 - Beta
Classifier: Framework :: Datasette
Classifier: Intended Audience :: Developers
Classifier: Intended Audience :: Science/Research
Classifier: Intended Audience :: End Users/Desktop
Classifier: Topic :: Database
Classifier: License :: OSI Approved :: Apache Software License
Classifier: Programming Language :: Python :: 3.13
Classifier: Programming Language :: Python :: 3.12
Classifier: Programming Language :: Python :: 3.11
Classifier: Programming Language :: Python :: 3.10
Classifier: Programming Language :: Python :: 3.9
Requires-Python: >=3.7
License-File: LICENSE
Requires-Dist: asgiref >=3.2.10
Requires-Dist: click >=7.1.1
Requires-Dist: click-default-group >=1.2.3
Requires-Dist: Jinja2 >=2.10.3
Requires-Dist: hupper >=1.9
Requires-Dist: httpx >=0.20
Requires-Dist: pluggy >=1.0
Requires-Dist: uvicorn >=0.11
Requires-Dist: aiofiles >=0.4
Requires-Dist: janus >=0.6.2
Requires-Dist: asgi-csrf >=0.9
Requires-Dist: PyYAML >=5.3
Requires-Dist: mergedeep >=1.1.1
Requires-Dist: itsdangerous >=1.1
Requires-Dist: setuptools
Requires-Dist: pip
Requires-Dist: platformdirs >=2.1.0
Requires-Dist: typing-extensions >=4.0.0
Requires-Dist: flexcache >=0.3
Requires-Dist: flexparser >=0.3
Provides-Extra: docs
Requires-Dist: furo ==2024.8.6 ; extra == 'docs'
Requires-Dist: sphinx-autobuild ; extra == 'docs'
Requires-Dist: codespell ; extra == 'docs'
Requires-Dist: blacken-docs ; extra == 'docs'
Requires-Dist: sphinx-copybutton ; extra == 'docs'
Provides-Extra: rich
Requires-Dist: rich ; extra == 'rich'
Provides-Extra: test
Requires-Dist: pytest >=5.2.2 ; extra == 'test'
Requires-Dist: pytest-xdist >=2.2.1 ; extra == 'test'
Requires-Dist: pytest-asyncio >=0.17 ; extra == 'test'
Requires-Dist: beautifulsoup4 >=4.8.1 ; extra == 'test'
Requires-Dist: black ==24.4.2 ; extra == 'test'
Requires-Dist: blacken-docs ==1.12.1 ; extra == 'test'
Requires-Dist: pytest-timeout >=1.4.2 ; extra == 'test'
Requires-Dist: trustme >=0.7 ; extra == 'test'
Requires-Dist: cogapp >=3.3.0 ; extra == 'test'
